utf_typecase/__init__.py
utf_typecase/banner.py
utf_typecase/client.py
utf_typecase/interfaces.py
utf_typecase/paste.py
utf_typecase/server.py
utf_typecase/cli/__init__.py
utf_typecase/cli/main.py
utf_typecase-0.2.0a1.dist-info/licenses/LICENSE
utf_typecase-0.2.0a1.dist-info/METADATA
utf_typecase-0.2.0a1.dist-info/WHEEL
utf_typecase-0.2.0a1.dist-info/entry_points.txt
utf_typecase-0.2.0a1.dist-info/top_level.txt
utf_typecase-0.2.0a1.dist-info/RECORD
