Metadata-Version: 2.4
Name: utf-typecase
Version: 0.2.0a1
Summary: Remote Unicode keyboard: select UTF characters in a browser and insert them on another device.
Author-email: AlexanderGoebel <lollybyte.git@gmail.com>
License: GPL-3.0-or-later
Project-URL: Homepage, https://github.com/lollybyte/utf-typecase
Project-URL: Repository, https://github.com/lollybyte/utf-typecase
Project-URL: Issues, https://github.com/lollybyte/utf-typecase/issues
Requires-Python: >=3.7
License-File: LICENSE
Requires-Dist: click
Requires-Dist: click-completion
Requires-Dist: click-pwsh
Requires-Dist: flask
Requires-Dist: requests
Requires-Dist: pyautogui
Requires-Dist: pyperclip
Dynamic: license-file
